<annotation>
	<folder></folder>
	<filename>new_face_171_jpg.rf.8e46277c8848086df244f61697eb6bd4.jpg</filename>
	<path>new_face_171_jpg.rf.8e46277c8848086df244f61697eb6bd4.jpg</path>
	<source>
		<database>roboflow.com</database>
	</source>
	<size>
		<width>640</width>
		<height>640</height>
		<depth>3</depth>
	</size>
	<segmented>0</segmented>
	<object>
		<name>yellow helmet</name>
		<pose>Unspecified</pose>
		<truncated>0</truncated>
		<difficult>0</difficult>
		<occluded>0</occluded>
		<bndbox>
			<xmin>61</xmin>
			<xmax>592</xmax>
			<ymin>26</ymin>
			<ymax>594</ymax>
		</bndbox>
		<polygon>
			<x1>60</x1>
			<y1>385</y1>
			<x2>105</x2>
			<y2>470</y2>
			<x3>272.5</x3>
			<y3>530</y3>
			<x4>520</x4>
			<y4>592.5</y4>
			<x5>564.219</x5>
			<y5>525</y5>
			<x6>565.391</x6>
			<y6>442.5</y6>
			<x7>590.625</x7>
			<y7>347.5</y7>
			<x8>590.742</x8>
			<y8>215</y8>
			<x9>510</x9>
			<y9>97.5</y9>
			<x10>415</x10>
			<y10>33.75</y10>
			<x11>335</x11>
			<y11>25</y11>
			<x12>242.5</x12>
			<y12>70</y12>
			<x13>212.5</x13>
			<y13>95</y13>
			<x14>120</x14>
			<y14>175</y14>
			<x15>93.75</x15>
			<y15>257.812</y15>
			<x16>85</x16>
			<y16>303.75</y16>
			<x17>60</x17>
			<y17>385</y17>
		</polygon>
	</object>
</annotation>
